[
    {
        "follower": 1,
        "followed": 2,
        "timestamp": "2023-04-01T10:00:00Z"
    },
    {
        "follower": 1,
        "followed": 3,
        "timestamp": "2023-04-01T10:15:00Z"
    },
    {
        "follower": 1,
        "followed": 4,
        "timestamp": "2023-04-01T10:30:00Z"
    },
    {
        "follower": 2,
        "followed": 1,
        "timestamp": "2023-04-01T10:45:00Z"
    },
    {
        "follower": 2,
        "followed": 3,
        "timestamp": "2023-04-01T11:00:00Z"
    },
    {
        "follower": 2,
        "followed": 4,
        "timestamp": "2023-04-01T11:15:00Z"
    },
    {
        "follower": 3,
        "followed": 1,
        "timestamp": "2023-04-01T11:30:00Z"
    },
    {
        "follower": 3,
        "followed": 2,
        "timestamp": "2023-04-01T11:45:00Z"
    },
    {
        "follower": 3,
        "followed": 4,
        "timestamp": "2023-04-01T12:00:00Z"
    },
    {
        "follower": 4,
        "followed": 1,
        "timestamp": "2023-04-01T12:15:00Z"
    },
    {
        "follower": 4,
        "followed": 2,
        "timestamp": "2023-04-01T12:30:00Z"
    },
    {
        "follower": 4,
        "followed": 3,
        "timestamp": "2023-04-01T12:45:00Z"
    }
]
